pdfs_rename-1.0.dist-info/DESCRIPTION.rst
pdfs_rename-1.0.dist-info/METADATA
pdfs_rename-1.0.dist-info/RECORD
pdfs_rename-1.0.dist-info/WHEEL
pdfs_rename-1.0.dist-info/entry_points.txt
pdfs_rename-1.0.dist-info/metadata.json
pdfs_rename-1.0.dist-info/top_level.txt
rename/__init__.py
rename/main.py
rename/utils.py
