Metadata-Version: 2.0
Name: pdfs-rename
Version: 1.0
Summary: Bulk rename PDFs.
Home-page: https://github.com/visgean/pdfs-rename
Author: Visgean
Author-email: visgean@gmail.com
License: MIT
Keywords: pdfs
Platform: UNKNOWN
Classifier: License :: OSI Approved :: MIT License
Classifier: Programming Language :: Python :: 3
Classifier: Programming Language :: Python :: 3.6
Requires-Dist: pdftotext
Requires-Dist: python-slugify
Requires-Dist: PyPDF2
